{"type":"root","label":null,"url":"","children":[{"type":"category","label":"Lampy wisz\u0105ce","url":"https:\/\/localhost\/3-lampy-wiszace","children":[],"open_in_new_window":false,"image_urls":[],"page_identifier":"category-3","current":false,"depth":1},{"type":"category","label":"Lampy zewn\u0119trzne","url":"https:\/\/localhost\/6-lampy-zewnetrzne","children":[],"open_in_new_window":false,"image_urls":[],"page_identifier":"category-6","current":false,"depth":1},{"type":"category","label":"Kinkiety","url":"https:\/\/localhost\/4-kinkiety","children":[],"open_in_new_window":false,"image_urls":[],"page_identifier":"category-4","current":false,"depth":1},{"type":"category","label":"Lampy sto\u0142owe","url":"https:\/\/localhost\/5-lampy-stolowe","children":[],"open_in_new_window":false,"image_urls":[],"page_identifier":"category-5","current":false,"depth":1}],"open_in_new_window":false,"image_urls":[],"page_identifier":null,"depth":0}